{
   "basePath": "http://localhost:8080/RestApiDoc-example",
   "apis": [
      {
         "methods": [
            {
               "headers": [],
               "bodyobject": null,
               "jsondocId": "aa401ad8-de25-44b1-ad54-365a7711f0fe",
               "consumes": [],
               "response": {
                  "mapKeyObject": "",
                  "jsondocId": "a14ddd13-dd75-4380-87a7-3f0d2abf10c2",
                  "mapValueObject": "",
                  "object": "author"
               },
               "pathparameters": [],
               "apierrors": [
                  {
                     "jsondocId": "198da519-0182-4c33-ac2f-4c26bfff375e",
                     "description": "Bad Request: missing parameters or bad message format",
                     "code": "400"
                  },
                  {
                     "jsondocId": "257f8845-f20c-4896-b5a1-143703595a27",
                     "description": "Unauthorized: must be auth",
                     "code": "401"
                  },
                  {
                     "jsondocId": "ce2617c6-9459-4e09-b736-e08e8caad179",
                     "description": "Forbidden: role error",
                     "code": "403"
                  },
                  {
                     "jsondocId": "fead57c3-371a-45ee-b05e-ff87ed820f3e",
                     "description": "Object not found",
                     "code": "404"
                  }
               ],
               "verb": "GET",
               "description": "List all authors",
               "queryparameters": [{
                  "jsondocId": "ff7673a0-3d29-4695-a1ce-5787213a9712",
                  "description": "Max number of author to retrieve",
                  "name": "max",
                  "allowedvalues": [],
                  "format": "",
                  "required": "true",
                  "type": "int"
               }],
               "path": "/author/list.json",
               "produces": ["application/json"],
               "methodName": "list"
            },
            {
               "headers": [],
               "bodyobject": null,
               "jsondocId": "ef9962cb-9837-465c-83d6-f4116a8ffb9d",
               "consumes": [],
               "response": {
                  "mapKeyObject": "",
                  "jsondocId": "66e44594-8d44-4293-9100-cd3095fd1c0b",
                  "mapValueObject": "",
                  "object": "author"
               },
               "pathparameters": [],
               "apierrors": [
                  {
                     "jsondocId": "c9722bd4-02c4-4988-88df-00a2b217d6b2",
                     "description": "Bad Request: missing parameters or bad message format",
                     "code": "400"
                  },
                  {
                     "jsondocId": "6985c3c1-c578-49be-981c-2c1cbd914a82",
                     "description": "Unauthorized: must be auth",
                     "code": "401"
                  },
                  {
                     "jsondocId": "eb23d0de-f76c-48e3-be02-bb79d9a5e8c9",
                     "description": "Forbidden: role error",
                     "code": "403"
                  },
                  {
                     "jsondocId": "840fe417-4334-4ebd-b841-7a39abf3c73c",
                     "description": "Object not found",
                     "code": "404"
                  }
               ],
               "verb": "GET",
               "description": "Get a authors with this lastname and firstname",
               "queryparameters": [
                  {
                     "jsondocId": "c86a3cbe-58a1-4378-bfb3-ea173d444263",
                     "description": "The lastname criteria",
                     "name": "lastname",
                     "allowedvalues": [],
                     "format": "",
                     "required": "true",
                     "type": ""
                  },
                  {
                     "jsondocId": "dbb31e48-bc71-46ff-8674-13e85b91ca6c",
                     "description": "The lastname criteria",
                     "name": "firstname",
                     "allowedvalues": [],
                     "format": "",
                     "required": "true",
                     "type": "String"
                  }
               ],
               "path": "/author/search.json",
               "produces": ["application/json"],
               "methodName": "search"
            },
            {
               "headers": [],
               "bodyobject": null,
               "jsondocId": "1f7750a6-ffc1-4a0a-8e22-6b3e97d6b156",
               "consumes": [],
               "response": {
                  "mapKeyObject": "",
                  "jsondocId": "821c27d7-75b4-4e0b-ad17-2cb1194b7a80",
                  "mapValueObject": "",
                  "object": "author"
               },
               "pathparameters": [],
               "apierrors": [
                  {
                     "jsondocId": "b1154602-4b15-4c60-84bc-cd6c5c33c565",
                     "description": "Bad Request: missing parameters or bad message format",
                     "code": "400"
                  },
                  {
                     "jsondocId": "28ba71e2-36ba-41bf-a3b4-0b5588f634c9",
                     "description": "Unauthorized: must be auth",
                     "code": "401"
                  },
                  {
                     "jsondocId": "a43db883-3330-4a84-91d0-b3e5c7dbf090",
                     "description": "Forbidden: role error",
                     "code": "403"
                  },
                  {
                     "jsondocId": "28452b4b-0aba-4cf5-911c-9e1ee04519b2",
                     "description": "Object not found",
                     "code": "404"
                  }
               ],
               "verb": "GET",
               "description": "Get author stats",
               "queryparameters": [{
                  "jsondocId": "1043a8a3-ca8f-4b7c-acde-fe1f4fd45b7b",
                  "description": "The author id",
                  "name": "id",
                  "allowedvalues": [],
                  "format": "",
                  "required": "true",
                  "type": "long"
               }],
               "path": "/author/stats.json",
               "produces": ["application/json"],
               "methodName": "stats"
            },
            {
               "headers": [],
               "bodyobject": null,
               "jsondocId": "a7b4e7c5-39f6-4983-9894-69db83d4967f",
               "consumes": [],
               "response": {
                  "mapKeyObject": "",
                  "jsondocId": "eb575363-3066-43c4-97de-dbce80c388ed",
                  "mapValueObject": "",
                  "object": "author"
               },
               "pathparameters": [{
                  "jsondocId": "1cc0d519-307c-4fe7-a528-39ad133033dd",
                  "description": "The author id",
                  "name": "id",
                  "allowedvalues": [],
                  "format": "",
                  "required": "true",
                  "type": "long"
               }],
               "apierrors": [
                  {
                     "jsondocId": "541c0351-0528-4d83-bb16-23acbd6f5c55",
                     "description": "Bad Request: missing parameters or bad message format",
                     "code": "400"
                  },
                  {
                     "jsondocId": "2b4d5471-cf6a-416e-b6e8-4272b1018e3e",
                     "description": "Unauthorized: must be auth",
                     "code": "401"
                  },
                  {
                     "jsondocId": "9d034ea3-dc99-4d8e-ac97-5b72f98b7592",
                     "description": "Forbidden: role error",
                     "code": "403"
                  },
                  {
                     "jsondocId": "eccd7e16-e97e-4215-84f5-73a21a6aa536",
                     "description": "Object not found",
                     "code": "404"
                  }
               ],
               "verb": "GET",
               "description": "Get an author",
               "queryparameters": [],
               "path": "/author/show/{id}.json",
               "produces": ["application/json"],
               "methodName": "show"
            },
            {
               "headers": [],
               "bodyobject": {
                  "mapKeyObject": "",
                  "jsondocId": "a62470a3-7ac2-47c4-a87f-aae31aab9663",
                  "mapValueObject": "",
                  "map": "",
                  "object": "nothing",
                  "multiple": "Unknow"
               },
               "jsondocId": "5d434944-4244-4e88-8671-571c048c02d0",
               "consumes": ["application/json"],
               "response": {
                  "mapKeyObject": "",
                  "jsondocId": "db302a32-fdb0-400c-9ecb-b263f27c39d0",
                  "mapValueObject": "",
                  "object": "[stats]"
               },
               "pathparameters": [{
                  "jsondocId": "a84d6ce1-9042-4d9b-9d3e-4649387f119a",
                  "description": "Max number of author to retrieve",
                  "name": "max",
                  "allowedvalues": [],
                  "format": "",
                  "required": "true",
                  "type": "int"
               }],
               "apierrors": [
                  {
                     "jsondocId": "f2b0f204-a54f-4990-9e1d-b215bc02cecd",
                     "description": "A custom error!",
                     "code": "400"
                  },
                  {
                     "jsondocId": "8ae650da-724f-45cc-8644-4d966c5922ac",
                     "description": "Unauthorized: must be auth",
                     "code": "401"
                  },
                  {
                     "jsondocId": "44db026d-bea0-45b2-ba41-b9968f3dc9de",
                     "description": "Forbidden: role error",
                     "code": "403"
                  },
                  {
                     "jsondocId": "19bb3586-781f-4478-a83a-35eb59af46c9",
                     "description": "Object not found",
                     "code": "404"
                  },
                  {
                     "jsondocId": "24dac43a-4318-4b98-a2ac-feceb23f2f15",
                     "description": "Object already exist",
                     "code": "409"
                  }
               ],
               "verb": "PUT",
               "description": "Get stats data for an author",
               "queryparameters": [],
               "path": "/a_custom_path/{max}.json",
               "produces": ["application/json"],
               "methodName": "someCustomPath"
            },
            {
               "headers": [],
               "bodyobject": null,
               "jsondocId": "6bcb0bd6-82b1-41f6-97db-ffe81135eaf6",
               "consumes": [],
               "response": {
                  "mapKeyObject": "",
                  "jsondocId": "82fd3d92-1467-4045-ab19-ffbdedc62c33",
                  "mapValueObject": "",
                  "object": "author"
               },
               "pathparameters": [{
                  "jsondocId": "d4a511a7-ad5a-4ece-9180-46f6e000d265",
                  "description": "The author id",
                  "name": "id",
                  "allowedvalues": [],
                  "format": "",
                  "required": "true",
                  "type": "long"
               }],
               "apierrors": [
                  {
                     "jsondocId": "e9882220-8cd6-4d46-ae35-6aa5cb5eba4e",
                     "description": "Bad Request: missing parameters or bad message format",
                     "code": "400"
                  },
                  {
                     "jsondocId": "bc5c2b2d-d7ef-4fb7-9793-73a58edd102d",
                     "description": "Unauthorized: must be auth",
                     "code": "401"
                  },
                  {
                     "jsondocId": "f1212637-27c9-4847-a5bc-24f2fc73b4bf",
                     "description": "Forbidden: role error",
                     "code": "403"
                  },
                  {
                     "jsondocId": "0623a901-eed6-42ef-af1c-420670d05024",
                     "description": "Object not found",
                     "code": "404"
                  }
               ],
               "verb": "GET",
               "description": "Get author avatar",
               "queryparameters": [{
                  "jsondocId": "98357627-2b3e-4f18-8ee9-823f1efd346e",
                  "description": "Width size for avatar",
                  "name": "size",
                  "allowedvalues": [],
                  "format": "",
                  "required": "true",
                  "type": "long"
               }],
               "path": "/author/avatar.jpg",
               "produces": ["application/json"],
               "methodName": "avatar"
            },
            {
               "headers": [],
               "bodyobject": null,
               "jsondocId": "fde3ae48-00a3-4200-8a6a-4e165439661a",
               "consumes": [],
               "response": {
                  "mapKeyObject": "",
                  "jsondocId": "a91e65f9-3517-47f4-bbcb-8f82eeb5220f",
                  "mapValueObject": "",
                  "object": "author"
               },
               "pathparameters": [{
                  "jsondocId": "e0b48bf7-3047-4248-ae07-567a80685530",
                  "description": "The author id",
                  "name": "id",
                  "allowedvalues": [],
                  "format": "",
                  "required": "true",
                  "type": "long"
               }],
               "apierrors": [
                  {
                     "jsondocId": "11c07458-1970-48db-ae9a-9346b167054b",
                     "description": "Bad Request: missing parameters or bad message format",
                     "code": "400"
                  },
                  {
                     "jsondocId": "8c3de5bc-0e33-4df6-9cc9-519c533c8d2e",
                     "description": "Unauthorized: must be auth",
                     "code": "401"
                  },
                  {
                     "jsondocId": "19313e77-cf1b-4af5-a1f1-b531b1114df5",
                     "description": "Forbidden: role error",
                     "code": "403"
                  },
                  {
                     "jsondocId": "d6f1abea-2616-4ece-8dc8-9aa544f67e42",
                     "description": "Object not found",
                     "code": "404"
                  }
               ],
               "verb": "GET",
               "description": "Get author avatar",
               "queryparameters": [{
                  "jsondocId": "59d9a425-e2a4-429d-8f4c-d86a37a685ee",
                  "description": "Width size for avatar",
                  "name": "size",
                  "allowedvalues": [],
                  "format": "",
                  "required": "true",
                  "type": "long"
               }],
               "path": "/author/avatar.png",
               "produces": ["application/json"],
               "methodName": "avatar"
            },
            {
               "headers": [],
               "bodyobject": {
                  "mapKeyObject": "",
                  "jsondocId": "45a9383f-ee6b-46c5-bfb4-f3ed0d72d9d3",
                  "mapValueObject": "",
                  "map": "",
                  "object": "author",
                  "multiple": "Unknow"
               },
               "jsondocId": "0c416341-31e5-48d9-a106-7f5995895282",
               "consumes": ["application/json"],
               "response": {
                  "mapKeyObject": "",
                  "jsondocId": "1fea0d4d-afbb-4d1a-aa51-1794f5151116",
                  "mapValueObject": "",
                  "object": "author"
               },
               "pathparameters": [],
               "apierrors": [
                  {
                     "jsondocId": "e66c1155-524b-4eb6-8cfc-c0d152c7f35c",
                     "description": "Bad Request: missing parameters or bad message format",
                     "code": "400"
                  },
                  {
                     "jsondocId": "f7495f95-2d48-428b-b048-4ddf0bfe9132",
                     "description": "Unauthorized: must be auth",
                     "code": "401"
                  },
                  {
                     "jsondocId": "e049f8b6-602a-4e2d-bd7d-08a52d2bbf74",
                     "description": "Forbidden: role error",
                     "code": "403"
                  },
                  {
                     "jsondocId": "bafe5c12-db88-466d-ba8b-504271873d25",
                     "description": "Object not found",
                     "code": "404"
                  },
                  {
                     "jsondocId": "af9812c6-9583-4a01-8ab8-c12fad499c5f",
                     "description": "Object already exist",
                     "code": "409"
                  }
               ],
               "verb": "POST",
               "description": "Generic query on an ",
               "queryparameters": [
                  {
                     "jsondocId": "aa569758-76d4-4c32-87fc-3f9b73d5c622",
                     "description": "The object id",
                     "name": "max",
                     "allowedvalues": [],
                     "format": "",
                     "required": "true",
                     "type": "long"
                  },
                  {
                     "jsondocId": "3d1420c4-481a-4051-b72b-41bde6bfb538",
                     "description": "The object id",
                     "name": "offfset",
                     "allowedvalues": [],
                     "format": "",
                     "required": "true",
                     "type": "long"
                  },
                  {
                     "jsondocId": "06bb3aa2-bc3f-4278-8f48-f0e1374a2b80",
                     "description": "The object id",
                     "name": "order",
                     "allowedvalues": [
                        "asc",
                        "desc"
                     ],
                     "format": "",
                     "required": "true",
                     "type": "string"
                  },
                  {
                     "jsondocId": "d5a165eb-ccfa-4138-8a64-9b5c64bd4e6f",
                     "description": "The object id",
                     "name": "sort",
                     "allowedvalues": [],
                     "format": "",
                     "required": "true",
                     "type": "string"
                  }
               ],
               "path": "/author/issue32.json",
               "produces": ["application/json"],
               "methodName": "issue32"
            }
         ],
         "jsondocId": "ecb46170-ad86-49e4-9e53-74f7c769fc43",
         "description": "Methods for managing authors",
         "name": "author services"
      },
      {
         "methods": [
            {
               "headers": [],
               "bodyobject": {
                  "mapKeyObject": "",
                  "jsondocId": "5df85073-c602-4b3b-9262-cd24454bd870",
                  "mapValueObject": "",
                  "map": "",
                  "object": "book",
                  "multiple": "Unknow"
               },
               "jsondocId": "f80902e8-b97d-4858-b2b9-15bcf0f913f9",
               "consumes": ["application/json"],
               "response": {
                  "mapKeyObject": "",
                  "jsondocId": "d1c9d707-5c43-4d63-9978-ad857ec48474",
                  "mapValueObject": "",
                  "object": "book"
               },
               "pathparameters": [],
               "apierrors": [
                  {
                     "jsondocId": "8d0a7344-d2ef-468c-aab5-642cc7b5e88e",
                     "description": "Bad Request: missing parameters or bad message format",
                     "code": "400"
                  },
                  {
                     "jsondocId": "cd9f181c-fbcf-48a4-8033-3a936a9158ec",
                     "description": "Unauthorized: must be auth",
                     "code": "401"
                  },
                  {
                     "jsondocId": "0dafbaf9-f7bc-40e8-9811-3817548c95d4",
                     "description": "Forbidden: role error",
                     "code": "403"
                  },
                  {
                     "jsondocId": "3cb30d08-b927-4e4f-beb3-fae233c58f09",
                     "description": "Object not found",
                     "code": "404"
                  },
                  {
                     "jsondocId": "8388e34b-2035-4f5f-be66-b3be6c553c50",
                     "description": "Object already exist",
                     "code": "409"
                  }
               ],
               "verb": "POST",
               "description": "Add a book on the store",
               "queryparameters": [],
               "path": "/api/book.json",
               "produces": ["application/json"],
               "methodName": "save"
            },
            {
               "headers": [],
               "bodyobject": null,
               "jsondocId": "235c8a8b-f68a-448c-a8d7-f0f6730f52bb",
               "consumes": [],
               "response": {
                  "mapKeyObject": "",
                  "jsondocId": "3b41c374-4ae8-4be2-94e1-ef71662a5f9e",
                  "mapValueObject": "",
                  "object": "book"
               },
               "pathparameters": [{
                  "jsondocId": "3680c2aa-eec6-4bc5-91a8-571f76691b07",
                  "description": "The book id",
                  "name": "id",
                  "allowedvalues": [],
                  "format": "",
                  "required": "true",
                  "type": "long"
               }],
               "apierrors": [
                  {
                     "jsondocId": "9c0f12b5-451b-43cf-8493-3f814a9b313a",
                     "description": "Bad Request: missing parameters or bad message format",
                     "code": "400"
                  },
                  {
                     "jsondocId": "bcdef900-e9c2-4a92-9ac2-50c918732422",
                     "description": "Unauthorized: must be auth",
                     "code": "401"
                  },
                  {
                     "jsondocId": "51ebabaa-b329-4180-9d0c-4d64e59c8a11",
                     "description": "Forbidden: role error",
                     "code": "403"
                  },
                  {
                     "jsondocId": "024798f0-e0ca-4586-9e35-52039bef16e9",
                     "description": "Object not found",
                     "code": "404"
                  }
               ],
               "verb": "DELETE",
               "description": "Delete a book",
               "queryparameters": [],
               "path": "/api/book/{id}.json",
               "produces": ["application/json"],
               "methodName": "delete"
            },
            {
               "headers": [],
               "bodyobject": {
                  "mapKeyObject": "",
                  "jsondocId": "3b24ea7b-3a04-48ba-a0cd-e45c7bcc9db1",
                  "mapValueObject": "",
                  "map": "",
                  "object": "book",
                  "multiple": "Unknow"
               },
               "jsondocId": "098c4535-f788-4583-a0b9-e787415020c0",
               "consumes": ["application/json"],
               "response": {
                  "mapKeyObject": "",
                  "jsondocId": "669e96e0-9482-43e1-802b-8e89de23c3ee",
                  "mapValueObject": "",
                  "object": "book"
               },
               "pathparameters": [{
                  "jsondocId": "df0347f9-a1a0-4e8f-be68-f4f95d9a63ec",
                  "description": "The book id",
                  "name": "id",
                  "allowedvalues": [],
                  "format": "",
                  "required": "true",
                  "type": "long"
               }],
               "apierrors": [
                  {
                     "jsondocId": "bd643dea-9f5c-48b1-b524-4f60811f662b",
                     "description": "Bad Request: missing parameters or bad message format",
                     "code": "400"
                  },
                  {
                     "jsondocId": "8c4666ef-5ded-4415-bf0a-14a3b77359b1",
                     "description": "Unauthorized: must be auth",
                     "code": "401"
                  },
                  {
                     "jsondocId": "1fbc870e-345b-459f-888a-7dcc624c03f3",
                     "description": "Forbidden: role error",
                     "code": "403"
                  },
                  {
                     "jsondocId": "7af9ec4e-7c01-4c9b-97de-c7cd0a45c151",
                     "description": "Object not found",
                     "code": "404"
                  },
                  {
                     "jsondocId": "76099638-2765-4739-aab1-10e704ce28d1",
                     "description": "Object already exist",
                     "code": "409"
                  }
               ],
               "verb": "PUT",
               "description": "Edit a book",
               "queryparameters": [],
               "path": "/api/book/{id}.json",
               "produces": ["application/json"],
               "methodName": "update"
            },
            {
               "headers": [],
               "bodyobject": null,
               "jsondocId": "86d5f310-ab26-44cd-b318-f67dd5904b40",
               "consumes": [],
               "response": {
                  "mapKeyObject": "",
                  "jsondocId": "796c208c-9c62-4758-b65f-1b215fdf5c5e",
                  "mapValueObject": "",
                  "object": "book"
               },
               "pathparameters": [{
                  "jsondocId": "6d0a0edf-7e3d-42b5-9772-270d4ed373af",
                  "description": "The book id",
                  "name": "id",
                  "allowedvalues": [],
                  "format": "",
                  "required": "true",
                  "type": "long"
               }],
               "apierrors": [
                  {
                     "jsondocId": "06a62580-1d84-43b1-86e5-57c7db508108",
                     "description": "Bad Request: missing parameters or bad message format",
                     "code": "400"
                  },
                  {
                     "jsondocId": "20a8f791-44e1-4577-b3de-dceb8426c611",
                     "description": "Unauthorized: must be auth",
                     "code": "401"
                  },
                  {
                     "jsondocId": "50a5817e-bffc-4dad-9656-429f1d9cdbd9",
                     "description": "Forbidden: role error",
                     "code": "403"
                  },
                  {
                     "jsondocId": "7e2152c5-0491-4259-8b86-3e74e72890d5",
                     "description": "Object not found",
                     "code": "404"
                  }
               ],
               "verb": "GET",
               "description": "Get a book",
               "queryparameters": [],
               "path": "/api/book/{id}.json",
               "produces": ["application/json"],
               "methodName": "show"
            },
            {
               "headers": [],
               "bodyobject": null,
               "jsondocId": "d320f676-d0eb-49e7-9d74-84252de3fee7",
               "consumes": [],
               "response": {
                  "mapKeyObject": "",
                  "jsondocId": "87cd923b-0843-48c7-8cae-2075966e89f5",
                  "mapValueObject": "",
                  "object": "book"
               },
               "pathparameters": [{
                  "jsondocId": "23abbd75-79b2-4074-8fc3-9b409114b666",
                  "description": "The author id",
                  "name": "id",
                  "allowedvalues": [],
                  "format": "",
                  "required": "true",
                  "type": "long"
               }],
               "apierrors": [
                  {
                     "jsondocId": "500944e5-05be-487a-9a82-d750d2847a79",
                     "description": "Bad Request: missing parameters or bad message format",
                     "code": "400"
                  },
                  {
                     "jsondocId": "3374ee02-3b9e-4e7c-ab53-11c49d06f3af",
                     "description": "Unauthorized: must be auth",
                     "code": "401"
                  },
                  {
                     "jsondocId": "85ba2b74-b452-4d1f-8257-3720078a9ec5",
                     "description": "Forbidden: role error",
                     "code": "403"
                  },
                  {
                     "jsondocId": "b466a19b-e542-4e18-b986-b7385188b425",
                     "description": "Object not found",
                     "code": "404"
                  }
               ],
               "verb": "GET",
               "description": "List books written by the author",
               "queryparameters": [],
               "path": "/api/author/{id}/book.json",
               "produces": ["application/json"],
               "methodName": "listByAuthor"
            }
         ],
         "jsondocId": "63b8eb30-8d90-4d4c-9c51-cc0c66bdd9c6",
         "description": "Methods for managing books",
         "name": "book services"
      }
   ],
   "objects": [
      {
         "jsondocId": "19af28f5-26fb-49a4-a07a-63d30bb4333a",
         "description": "An author stats",
         "name": "[stats]",
         "fields": [
            {
               "jsondocId": "90c4ef2c-de99-4d40-841b-d95f1ff0709b",
               "description": "The author fullname",
               "presentInResponse": false,
               "mandatory": false,
               "name": "fullname",
               "allowedvalues": null,
               "useForCreation": false,
               "format": null,
               "defaultValue": null,
               "type": "String",
               "multiple": "false"
            },
            {
               "jsondocId": "b4b74e05-3e3c-47ff-ad6e-273a1f1098d1",
               "description": "The number of books created by this author",
               "presentInResponse": false,
               "mandatory": false,
               "name": "numberOfBook",
               "allowedvalues": null,
               "useForCreation": false,
               "format": null,
               "defaultValue": null,
               "type": "Integer",
               "multiple": "false"
            }
         ]
      },
      {
         "jsondocId": "fc4d58af-0c61-4cf2-867a-b406f8682212",
         "description": "An author write books",
         "name": "author",
         "fields": [
            {
               "jsondocId": "de7a1677-5c8f-4ba7-a719-81d7a4248d62",
               "description": "The firstname of the author",
               "presentInResponse": true,
               "mandatory": true,
               "name": "firstname",
               "allowedvalues": null,
               "useForCreation": true,
               "format": null,
               "defaultValue": null,
               "type": "String",
               "multiple": "false"
            },
            {
               "jsondocId": "b7a2498f-03fc-4a26-903b-c29e6aa341a5",
               "description": "The lastname of the author",
               "presentInResponse": true,
               "mandatory": true,
               "name": "lastname",
               "allowedvalues": null,
               "useForCreation": true,
               "format": null,
               "defaultValue": null,
               "type": "String",
               "multiple": "false"
            },
            {
               "jsondocId": "c3f30e44-81d9-4054-a8d2-ea7de31b2ef7",
               "description": "The first and lastname",
               "presentInResponse": true,
               "mandatory": false,
               "name": "fullname",
               "allowedvalues": null,
               "useForCreation": false,
               "format": null,
               "defaultValue": null,
               "type": "String",
               "multiple": "false"
            },
            {
               "jsondocId": "5e059fdb-4765-47b9-b11b-83cd0ca29f7b",
               "description": "Books id written by this author",
               "presentInResponse": true,
               "mandatory": false,
               "name": "books",
               "allowedvalues": null,
               "useForCreation": false,
               "format": null,
               "defaultValue": null,
               "type": "List",
               "multiple": "true"
            },
            {
               "jsondocId": "1882a2f9-fe58-49fd-915c-a8e6ba906058",
               "description": "The birthday date of the author",
               "presentInResponse": false,
               "mandatory": false,
               "name": "birthday",
               "allowedvalues": null,
               "useForCreation": true,
               "format": null,
               "defaultValue": "01/01/1970",
               "type": "Date",
               "multiple": "false"
            },
            {
               "jsondocId": "3a957712-4fcd-44ef-af28-bf5de691f9d3",
               "description": null,
               "presentInResponse": false,
               "mandatory": null,
               "name": "id",
               "allowedvalues": null,
               "useForCreation": null,
               "format": null,
               "defaultValue": null,
               "type": "Long",
               "multiple": "false"
            }
         ]
      },
      {
         "jsondocId": "4dcfa708-2fc5-4867-bb21-4e4b5661babf",
         "description": "A book available on the store",
         "name": "book",
         "fields": [
            {
               "jsondocId": "0cf34a42-f117-4cec-8746-723fd20339d0",
               "description": "The author of the book",
               "presentInResponse": true,
               "mandatory": true,
               "name": "author",
               "allowedvalues": null,
               "useForCreation": true,
               "format": null,
               "defaultValue": null,
               "type": "Author",
               "multiple": "false"
            },
            {
               "jsondocId": "00983c8b-e359-441e-bc07-559b64737b58",
               "description": "The book category",
               "presentInResponse": true,
               "mandatory": true,
               "name": "category",
               "allowedvalues": null,
               "useForCreation": true,
               "format": null,
               "defaultValue": null,
               "type": "String",
               "multiple": "false"
            },
            {
               "jsondocId": "a83fa710-42f9-4f97-aa55-f11e2feaf1fb",
               "description": null,
               "presentInResponse": null,
               "mandatory": null,
               "name": "id",
               "allowedvalues": null,
               "useForCreation": null,
               "format": null,
               "defaultValue": null,
               "type": "Long",
               "multiple": "false"
            },
            {
               "jsondocId": "79375612-9267-4728-9f17-b02e9424e14f",
               "description": "The title of the book",
               "presentInResponse": true,
               "mandatory": true,
               "name": "title",
               "allowedvalues": null,
               "useForCreation": true,
               "format": null,
               "defaultValue": null,
               "type": "String",
               "multiple": "false"
            },
            {
               "jsondocId": "825de7d9-5110-47f3-bab1-cf43bbdc07e7",
               "description": "Year published for this book",
               "presentInResponse": true,
               "mandatory": true,
               "name": "year",
               "allowedvalues": null,
               "useForCreation": true,
               "format": null,
               "defaultValue": null,
               "type": "Integer",
               "multiple": "false"
            }
         ]
      }
   ],
   "version": "0.1.1"
}